MANIFEST.in
README.md
requirements.txt
setup.py
sunny/__init__.py
sunny/compat.py
sunny/sunny.py
sunny.egg-info/PKG-INFO
sunny.egg-info/SOURCES.txt
sunny.egg-info/dependency_links.txt
sunny.egg-info/requires.txt
sunny.egg-info/top_level.txt