Metadata-Version: 1.1
Name: sunny
Version: 0.0.4
Summary: Minimalistic interface to Solr.
Home-page: http://sunny.dogan.se/
Author: Deniz Dogan
Author-email: deniz@dogan.se
License: BSD
Keywords: solr search
Platform: UNKNOWN
Classifier: Development Status :: 3 - Alpha
Classifier: Intended Audience :: Developers
Classifier: License :: OSI Approved :: BSD License
Classifier: Programming Language :: Python :: 2
Classifier: Topic :: Internet :: WWW/HTTP :: Indexing/Search
